mats/__init__.py
mats/archiving.py
mats/test.py
mats/test_sequence.py
mats/tkwidgets.py
mats/version.py
mats-0.74.10.dist-info/METADATA
mats-0.74.10.dist-info/WHEEL
mats-0.74.10.dist-info/top_level.txt
mats-0.74.10.dist-info/RECORD
