Metadata-Version: 2.2
Name: mats
Version: 0.74.10
Summary: Manufacturing Automated Test System, a framework for building device testing quickly and consistently
Author-email: "Jason R. Jones" <slightlynybbled@gmail.com>
Project-URL: Documentation, https://slightlynybbled.github.io/mats/
Project-URL: Repository, https://github.com/slightlynybbled/mats
Classifier: Development Status :: 4 - Beta
Classifier: Programming Language :: Python :: 3
Classifier: License :: OSI Approved :: MIT License
Classifier: Operating System :: OS Independent
Classifier: Intended Audience :: Manufacturing
Classifier: Natural Language :: English
Requires-Python: >=3.10
Requires-Dist: coloredlogs>=15.0.0
Requires-Dist: sigfig>=1.3
